lclib/__init__.py
lclib/characterization/__init__.py
lclib/characterization/input_capacitance.py
lclib/characterization/ngspice_simulation.py
lclib/characterization/piece_wise_linear.py
lclib/characterization/standalone.py
lclib/characterization/test_ngspice_shared.py
lclib/characterization/timing_combinatorial.py
lclib/characterization/timing_sequential.py
lclib/characterization/util.py
lclib/liberty/__init__.py
lclib/liberty/merge.py
lclib/liberty/util.py
lclib/liberty/visualize.py
lclib/logic/__init__.py
lclib/logic/cmos_sim.py
lclib/logic/cmos_synth.py
lclib/logic/graph_enumeration.py
lclib/logic/util.py
lclib/transistor_sizing/__init__.py
lclib/transistor_sizing/width_opt.py
librecell_lib-0.0.3.post0.dist-info/LICENSE
librecell_lib-0.0.3.post0.dist-info/METADATA
librecell_lib-0.0.3.post0.dist-info/WHEEL
librecell_lib-0.0.3.post0.dist-info/entry_points.txt
librecell_lib-0.0.3.post0.dist-info/top_level.txt
librecell_lib-0.0.3.post0.dist-info/RECORD
