Metadata-Version: 2.1
Name: librecell-lib
Version: 0.0.3.post0
Summary: CMOS standard cell characterization kit.
Home-page: https://codeberg.org/tok/librecell
Author: T. Kramer
Author-email: dont@spam.me
License: AGPL
Keywords: cmos cell characterization vlsi asic
Platform: UNKNOWN
Classifier: License :: OSI Approved :: GNU Affero General Public License v3 or later (AGPLv3+)
Classifier: Development Status :: 3 - Alpha
Classifier: Topic :: Scientific/Engineering
Classifier: Topic :: Scientific/Engineering :: Electronic Design Automation (EDA)
Classifier: Programming Language :: Python :: 3
Requires-Dist: librecell-common
Requires-Dist: numpy
Requires-Dist: sympy
Requires-Dist: matplotlib
Requires-Dist: networkx
Requires-Dist: pyspice
Requires-Dist: scipy
Requires-Dist: liberty-parser
